[
  {
    "fields": {
      "person": 4,
      "pcp": "78-908978",
      "user_company_benefit_plan_option": 4
    },
    "model": "app.enrolled",
    "pk": 6
  },
  {
    "fields": {
      "person": 3,
      "pcp": "78-890868",
      "user_company_benefit_plan_option": 4
    },
    "model": "app.enrolled",
    "pk": 7
  },
  {
    "fields": {
      "person": 4,
      "pcp": null,
      "user_company_benefit_plan_option": 5
    },
    "model": "app.enrolled",
    "pk": 8
  },
  {
    "fields": {
      "person": 3,
      "pcp": null,
      "user_company_benefit_plan_option": 5
    },
    "model": "app.enrolled",
    "pk": 9
  },
  {
    "fields": {
      "person": 3,
      "pcp": null,
      "user_company_benefit_plan_option": 6
    },
    "model": "app.enrolled",
    "pk": 10
  }
]