[
  { 
    "model": "app.BenefitDetails",
    "pk": 1,
    "fields":{
    	"value" : "$2000",
      "benefit_policy_key": 1,
      "benefit_policy_type": 1,
      "benefit_plan": 1
    }
  },
  { 
    "model": "app.BenefitDetails",
    "pk": 2,
    "fields":{
    	"value" : "$4000",
      "benefit_policy_key": 2,
      "benefit_policy_type": 1,
      "benefit_plan": 1
    }
  },
  { 
    "model": "app.BenefitDetails",
    "pk": 3,
    "fields":{
    	"value" : "100% after deductible",
      "benefit_policy_key": 3,
      "benefit_policy_type": 1,
      "benefit_plan": 1
    }
  },
  { 
    "model": "app.BenefitDetails",
    "pk": 4,
    "fields":{
    	"value" : "100% after deductible",
      "benefit_policy_key": 4,
      "benefit_policy_type": 1,
      "benefit_plan": 1
    }
  },
  { 
    "model": "app.BenefitDetails",
    "pk": 5,
    "fields":{
    	"value" : "100% after deductible",
      "benefit_policy_key": 5,
      "benefit_policy_type": 1,
      "benefit_plan": 1
    }
  },
  { 
    "model": "app.BenefitDetails",
    "pk": 6,
    "fields":{
    	"value" : "100% after deductible",
      "benefit_policy_key": 6,
      "benefit_policy_type": 1,
      "benefit_plan": 1
    }
  },
  { 
    "model": "app.BenefitDetails",
    "pk": 7,
    "fields":{
    	"value" : "$40-Copay",
      "benefit_policy_key": 7,
      "benefit_policy_type": 1,
      "benefit_plan": 1
    }
  },
  { 
    "model": "app.BenefitDetails",
    "pk": 8,
    "fields":{
    	"value" : "$15/$25/$45",
      "benefit_policy_key": 8,
      "benefit_policy_type": 1,
      "benefit_plan": 1
    }
  },
  { 
    "model": "app.BenefitDetails",
    "pk": 9,
    "fields":{
      "value" : "$30/$50/$135",
      "benefit_policy_key": 9,
      "benefit_policy_type": 1,
      "benefit_plan": 1
    }
  },
  { 
    "model": "app.BenefitDetails",
    "pk": 10,
    "fields":{
      "value" : "Unlimited",
      "benefit_policy_key": 10,
      "benefit_policy_type": 1,
      "benefit_plan": 1
    }
  },
  { 
    "model": "app.BenefitDetails",
    "pk": 11,
    "fields":{
      "value" : "Yes",
      "benefit_policy_key": 11,
      "benefit_policy_type": 1,
      "benefit_plan": 1
    }
  },
  { 
    "model": "app.BenefitDetails",
    "pk": 12,
    "fields":{
      "value" : "$2000",
      "benefit_policy_key": 1,
      "benefit_policy_type": 1,
      "benefit_plan": 2
    }
  },
  { 
    "model": "app.BenefitDetails",
    "pk": 13,
    "fields":{
      "value" : "$4000",
      "benefit_policy_key": 2,
      "benefit_policy_type": 1,
      "benefit_plan": 2
    }
  },
  { 
    "model": "app.BenefitDetails",
    "pk": 14,
    "fields":{
      "value" : "100% after deductible",
      "benefit_policy_key": 3,
      "benefit_policy_type": 1,
      "benefit_plan": 2
    }
  },
  { 
    "model": "app.BenefitDetails",
    "pk": 15,
    "fields":{
      "value" : "100% after deductible",
      "benefit_policy_key": 4,
      "benefit_policy_type": 1,
      "benefit_plan": 2
    }
  },
  { 
    "model": "app.BenefitDetails",
    "pk": 16,
    "fields":{
      "value" : "100% after deductible",
      "benefit_policy_key": 5,
      "benefit_policy_type": 1,
      "benefit_plan": 2
    }
  },
  { 
    "model": "app.BenefitDetails",
    "pk": 17,
    "fields":{
      "value" : "100% after deductible",
      "benefit_policy_key": 6,
      "benefit_policy_type": 1,
      "benefit_plan": 2
    }
  },
  { 
    "model": "app.BenefitDetails",
    "pk": 18,
    "fields":{
      "value" : "$40-Copay",
      "benefit_policy_key": 7,
      "benefit_policy_type": 1,
      "benefit_plan": 2
    }
  },
  { 
    "model": "app.BenefitDetails",
    "pk": 19,
    "fields":{
      "value" : "$15/$25/$45",
      "benefit_policy_key": 8,
      "benefit_policy_type": 1,
      "benefit_plan": 2
    }
  },
  { 
    "model": "app.BenefitDetails",
    "pk": 20,
    "fields":{
      "value" : "$30/$50/$135",
      "benefit_policy_key": 9,
      "benefit_policy_type": 1,
      "benefit_plan": 2
    }
  },
  { 
    "model": "app.BenefitDetails",
    "pk": 21,
    "fields":{
      "value" : "Unlimited",
      "benefit_policy_key": 10,
      "benefit_policy_type": 1,
      "benefit_plan": 2
    }
  },
  { 
    "model": "app.BenefitDetails",
    "pk": 22,
    "fields":{
      "value" : "Yes",
      "benefit_policy_key": 11,
      "benefit_policy_type": 1,
      "benefit_plan": 2
    }
  },
    { 
    "model": "app.BenefitDetails",
    "pk": 23,
    "fields":{
      "value" : "$2000",
      "benefit_policy_key": 1,
      "benefit_policy_type": 2,
      "benefit_plan": 2
    }
  },
  { 
    "model": "app.BenefitDetails",
    "pk": 24,
    "fields":{
      "value" : "$4000",
      "benefit_policy_key": 2,
      "benefit_policy_type": 2,
      "benefit_plan": 2
    }
  },
  { 
    "model": "app.BenefitDetails",
    "pk": 25,
    "fields":{
      "value" : "100% after deductible",
      "benefit_policy_key": 3,
      "benefit_policy_type": 2,
      "benefit_plan": 2
    }
  },
  { 
    "model": "app.BenefitDetails",
    "pk": 26,
    "fields":{
      "value" : "100% after deductible",
      "benefit_policy_key": 4,
      "benefit_policy_type": 2,
      "benefit_plan": 2
    }
  },
  { 
    "model": "app.BenefitDetails",
    "pk": 27,
    "fields":{
      "value" : "100% after deductible",
      "benefit_policy_key": 5,
      "benefit_policy_type": 2,
      "benefit_plan": 2
    }
  },
  { 
    "model": "app.BenefitDetails",
    "pk": 28,
    "fields":{
      "value" : "100% after deductible",
      "benefit_policy_key": 6,
      "benefit_policy_type": 2,
      "benefit_plan": 2
    }
  },
  { 
    "model": "app.BenefitDetails",
    "pk": 29,
    "fields":{
      "value" : "$40-Copay",
      "benefit_policy_key": 7,
      "benefit_policy_type": 2,
      "benefit_plan": 2
    }
  },
  { 
    "model": "app.BenefitDetails",
    "pk": 30,
    "fields":{
      "value" : "$15/$25/$45",
      "benefit_policy_key": 8,
      "benefit_policy_type": 2,
      "benefit_plan": 2
    }
  },
  { 
    "model": "app.BenefitDetails",
    "pk": 31,
    "fields":{
      "value" : "$30/$50/$135",
      "benefit_policy_key": 9,
      "benefit_policy_type": 2,
      "benefit_plan": 2
    }
  },
  { 
    "model": "app.BenefitDetails",
    "pk": 32,
    "fields":{
      "value" : "Unlimited",
      "benefit_policy_key": 10,
      "benefit_policy_type": 2,
      "benefit_plan": 2
    }
  },
  { 
    "model": "app.BenefitDetails",
    "pk": 33,
    "fields":{
      "value" : "Yes",
      "benefit_policy_key": 11,
      "benefit_policy_type": 2,
      "benefit_plan": 2
    }
  }
]





